oceania/__init__.py
oceania/__main__.py
oceania/main/__init__.py
oceania/main/cli.py
oceania/main/client.py
oceania/main/settings.py
oceania/main/utils.py
oceania_query_fasta-0.1.7.dist-info/LICENSE
oceania_query_fasta-0.1.7.dist-info/METADATA
oceania_query_fasta-0.1.7.dist-info/WHEEL
oceania_query_fasta-0.1.7.dist-info/entry_points.txt
oceania_query_fasta-0.1.7.dist-info/top_level.txt
oceania_query_fasta-0.1.7.dist-info/RECORD
