Metadata-Version: 2.1
Name: oceania-query-fasta
Version: 0.1.7
Summary: A small package to query data from the OceanIA services
Home-page: https://gitlab.com/Inria-Chile/oceania/oceania-query-fasta
Author: Inria Chile
Author-email: desarrollo@inria.cl
License: UNKNOWN
Platform: UNKNOWN
Classifier: Development Status :: 2 - Pre-Alpha
Classifier: Intended Audience :: Science/Research
Classifier: Programming Language :: Python :: 3
Classifier: Programming Language :: Python :: 3.6
Classifier: Programming Language :: Python :: 3.7
Classifier: Programming Language :: Python :: 3.8
Classifier: Programming Language :: Python :: 3.9
Classifier: Topic :: Software Development :: Libraries :: Python Modules
Classifier: Topic :: Utilities
Requires-Python: >=3.6
License-File: LICENSE
Requires-Dist: requests (==2.*)
Requires-Dist: click (==7.*)
Requires-Dist: pandas (==1.*)
